aws_recommendation_a20/__init__.py
aws_recommendation_a20/cloudwatch.py
aws_recommendation_a20/cost_estimations.py
aws_recommendation_a20/dynamodb.py
aws_recommendation_a20/ebs.py
aws_recommendation_a20/ec2.py
aws_recommendation_a20/elb.py
aws_recommendation_a20/kms.py
aws_recommendation_a20/rds.py
aws_recommendation_a20/recommendation.py
aws_recommendation_a20/redshift.py
aws_recommendation_a20/s3.py
aws_recommendation_a20/truted_advisor.py
aws_recommendation_a20/utils.py
aws_recommendation_a20-0.1.11.dist-info/LICENCE
aws_recommendation_a20-0.1.11.dist-info/METADATA
aws_recommendation_a20-0.1.11.dist-info/WHEEL
aws_recommendation_a20-0.1.11.dist-info/top_level.txt
aws_recommendation_a20-0.1.11.dist-info/RECORD
